onlyday/__init__.py
onlyday/collections.py
onlyday/day.py
onlyday/utilities.py
OnlyDay-0.1.1.dist-info/LICENSE
OnlyDay-0.1.1.dist-info/METADATA
OnlyDay-0.1.1.dist-info/WHEEL
OnlyDay-0.1.1.dist-info/top_level.txt
OnlyDay-0.1.1.dist-info/RECORD
