Metadata-Version: 2.1
Name: OnlyDay
Version: 0.1.1
Summary: Library that introduces a Day datatype that is universal across every year
Author-email: "Christopher O. Tubbs" <christopherotubbs@gmail.com>
License: MIT License
Project-URL: Homepage, https://github.com/christophertubbs/OnlyDay
Project-URL: Issues, https://github.com/christophertubbs/OnlyDay/issues
Classifier: Development Status :: 3 - Alpha
Classifier: Intended Audience :: Developers
Classifier: License :: OSI Approved :: MIT License
Classifier: Programming Language :: Python :: 3.8
Classifier: Programming Language :: Python :: 3.9
Classifier: Programming Language :: Python :: 3.10
Classifier: Programming Language :: Python :: 3.11
Classifier: Programming Language :: Python :: 3.12
Classifier: Topic :: Software Development :: Libraries
Classifier: Operating System :: OS Independent
Classifier: Topic :: Software Development :: Libraries
Requires-Python: >=3.6
License-File: LICENSE
Requires-Dist: python-dateutil
Requires-Dist: pytz
Provides-Extra: dev
Requires-Dist: pytest; extra == "dev"
